scientisttseries/__init__.py
scientisttseries/arfirma.py
scientisttseries/tsaplots.py
scientisttseries/tsatests.py
scientisttseries/uniroot.py
scientisttseries/utils.py
scientisttseries-0.0.2.dist-info/LICENSE
scientisttseries-0.0.2.dist-info/METADATA
scientisttseries-0.0.2.dist-info/WHEEL
scientisttseries-0.0.2.dist-info/top_level.txt
scientisttseries-0.0.2.dist-info/RECORD
