Metadata-Version: 2.1
Name: scientisttseries
Version: 0.0.2
Summary: Python library for times series
Home-page: UNKNOWN
Author: Duverier DJIFACK ZEBAZE
Author-email: duverierdjifack@gmail.com
License: UNKNOWN
Platform: UNKNOWN
Classifier: Programming Language :: Python :: 3
Classifier: License :: OSI Approved :: MIT License
Classifier: Operating System :: OS Independent
Requires-Python: >=3.10
License-File: LICENSE
Requires-Dist: numpy (>=1.23.5)
Requires-Dist: matplotlib (>=3.5.3)
Requires-Dist: scikit-learn (>=1.2.2)
Requires-Dist: pandas (>=1.5.3)
Requires-Dist: mapply (>=0.1.21)
Requires-Dist: plotnine (>=0.10.1)
Requires-Dist: plydata (>=0.4.3)
